.coveragerc
.testr.conf
HACKING.rst
LICENSE
MANIFEST.in
README.md
openstack-common.conf
requirements.txt
run_tests.sh
setup.cfg
setup.py
test-requirements.txt
tox.ini
examples/README.rst
examples/server_example.py
python_seamicroclient.egg-info/PKG-INFO
python_seamicroclient.egg-info/SOURCES.txt
python_seamicroclient.egg-info/dependency_links.txt
python_seamicroclient.egg-info/not-zip-safe
python_seamicroclient.egg-info/pbr.json
python_seamicroclient.egg-info/requires.txt
python_seamicroclient.egg-info/top_level.txt
seamicroclient/__init__.py
seamicroclient/base.py
seamicroclient/client.py
seamicroclient/exceptions.py
seamicroclient/utils.py
seamicroclient/openstack/__init__.py
seamicroclient/openstack/common/__init__.py
seamicroclient/openstack/common/gettextutils.py
seamicroclient/openstack/common/strutils.py
seamicroclient/openstack/common/timeutils.py
seamicroclient/openstack/common/uuidutils.py
seamicroclient/openstack/common/py3kcompat/__init__.py
seamicroclient/openstack/common/py3kcompat/urlutils.py
seamicroclient/tests/__init__.py
seamicroclient/tests/fakes.py
seamicroclient/tests/test_base.py
seamicroclient/tests/test_client.py
seamicroclient/tests/test_http.py
seamicroclient/tests/utils.py
seamicroclient/tests/functional/__init__.py
seamicroclient/tests/functional/v2/__init__.py
seamicroclient/tests/functional/v2/test_pools.py
seamicroclient/tests/functional/v2/test_servers.py
seamicroclient/tests/functional/v2/test_volumes.py
seamicroclient/tests/v2/__init__.py
seamicroclient/tests/v2/fakes.py
seamicroclient/tests/v2/test_SMCards.py
seamicroclient/tests/v2/test_chassis.py
seamicroclient/tests/v2/test_disks.py
seamicroclient/tests/v2/test_fantrays.py
seamicroclient/tests/v2/test_interfaces.py
seamicroclient/tests/v2/test_pools.py
seamicroclient/tests/v2/test_powersupplies.py
seamicroclient/tests/v2/test_scards.py
seamicroclient/tests/v2/test_servers.py
seamicroclient/tests/v2/test_system.py
seamicroclient/tests/v2/test_volumes.py
seamicroclient/v2/__init__.py
seamicroclient/v2/chassis.py
seamicroclient/v2/client.py
seamicroclient/v2/disks.py
seamicroclient/v2/fantrays.py
seamicroclient/v2/interfaces.py
seamicroclient/v2/pools.py
seamicroclient/v2/powersupplies.py
seamicroclient/v2/scards.py
seamicroclient/v2/servers.py
seamicroclient/v2/smcards.py
