Metadata-Version: 1.1
Name: python-seamicroclient
Version: 0.2.1.post6
Summary: Client library for Seamicro chassis API
Home-page: https://github.com/seamicro/python-seamicroclient
Author: AMD
Author-email: harshada.kakad@izeltech.com
License: Apache License, Version 2.0
Platform: UNKNOWN
Classifier: Development Status :: 4 - Beta
Classifier: Environment :: Console
Classifier: Environment :: Web Environment
Classifier: Intended Audience :: Developers
Classifier: Intended Audience :: Information Technology
Classifier: License :: OSI Approved :: Apache Software License
Classifier: Operating System :: OS Independent
Classifier: Programming Language :: Python
